src/emily0_9/__init__.py
src/emily0_9/code_point_testing.py
src/emily0_9/css_emitting.py
src/emily0_9/css_parsing.py
src/emily0_9/emily.py
src/emily0_9/emily_runner.py
src/emily0_9/html_css_parsing.py
src/emily0_9/html_emitting.py
src/emily0_9/html_parsing.py
src/emily0_9/html_texting.py
src/emily0_9/looking_ahead.py
src/emily0_9/mle_emitting.py
src/emily0_9/mle_parsing.py
src/emily0_9/page_laying_out.py
src/emily0_9/persisting.py
src/emily0_9/rendering.py
src/emily0_9/string_parsing.py
src/emily0_9/text_emitting.py
src/emily0_9/text_printing.py
src/emily0_9/text_tokenizing.py
src/emily0_9/texting.py
src/emily0_9/unicode_io.py
emily_editor-0.9.dist-info/METADATA
emily_editor-0.9.dist-info/WHEEL
emily_editor-0.9.dist-info/licenses/LICENCE
emily_editor-0.9.dist-info/RECORD
