Metadata-Version: 2.1
Name: Emily_editor
Version: 0.9
Summary: WYSIWYG editor using subset of HTML5 for storage
Author-email: rnb <talkguibits@gmail.com>
License-File: LICENCE
Classifier: License :: OSI Approved :: GNU General Public License (GPL)
Classifier: Operating System :: OS Independent
Classifier: Programming Language :: Python :: 3
Requires-Python: >=3.8
